[
  {
    "file_path": "./input/唐诗三百首.pdf",
    "qa_pairs": [
      {
        "question": "古人认为什么是实现人生幸福的金钥匙？",
        "answer": "经典中蕴含的修身、齐家、治国、平天下的大道理。"
      },
      {
        "question": "阅读经典可以获得哪些益处？",
        "answer": "获得身心的健康，拥有美好的家庭，处理好各种人际关系，成就事业，创造财富；解决当前问题，庇荫将来；获得物质富足和精神家园。"
      },
      {
        "question": "读古人书获得真实利益的关键是什么？",
        "answer": "诚与敬二字。"
      },
      {
        "question": "《唐诗三百首》的编选者是谁？",
        "answer": "蘅塘退士（原名孙洙）。"
      },
      {
        "question": "《唐诗三百首》的编选标准是什么？",
        "answer": "专就唐诗中脍炙人口之作，择其尤要者。"
      },
      {
        "question": "《唐诗三百首》中共选入多少位唐代诗人？",
        "answer": "七十七位。"
      },
      {
        "question": "《唐诗三百首》中共选入多少首唐诗？",
        "answer": "三百一十九首。"
      },
      {
        "question": "五言古诗的代表诗人有哪些？",
        "answer": "李白、杜甫、王维、孟浩然、韦应物等。"
      },
      {
        "question": "七言古诗的代表诗人有哪些？",
        "answer": "李白、杜甫、韩愈等。"
      },
      {
        "question": "五言律诗的代表诗人有哪些？",
        "answer": "王昌龄、王维、孟浩然、李白、杜甫、刘长卿。"
      },
      {
        "question": "七言律诗的代表诗人有哪些？",
        "answer": "王维、杜甫、李商隐、杜牧、罗隐等。"
      },
      {
        "question": "五绝和七绝的名家有哪些？",
        "answer": "李白、王维、王昌龄、韦应物、杜牧、刘禹锡等。"
      },
      {
        "question": "《唐诗三百首》中乐府诗的作用是什么？",
        "answer": "体现其与音乐的密切关系，并可以看出律诗等由乐府诗发展而来的痕迹。"
      },
      {
        "question": "《唐诗三百首》选录了多少位唐代诗人？占唐代可考诗人的百分比是多少？",
        "answer": "《唐诗三百首》选录了77位唐代诗人，占唐代可考诗人的2.79%。"
      },
      {
        "question": "《唐诗三百首》的诗歌总体上符合什么样的审美要求？",
        "answer": "总体上符合当时温柔敦厚、'乐而不淫，哀而不伤'的诗歌审美要求。"
      },
      {
        "question": "俗话'熟读唐诗三百首，不会作诗也会吟'说明了什么？",
        "answer": "说明了《唐诗三百首》作为启蒙教材的成功性，通过吟诵可以领会诗歌意趣，提升文化修养。"
      },
      {
        "question": "张九龄《感遇之一》中'双翠鸟'指的是什么？",
        "answer": "指翡翠鸟，雄为翡，雌为翠，毛色华丽多彩。"
      },
      {
        "question": "李白《月下独酌》中'永结无情游'的'无情游'是什么意思？",
        "answer": "指忘却世情的交游。"
      },
      {
        "question": "杜甫《望岳》中'阴阳割昏晓'的'割'字有何妙处？",
        "answer": "用夸张手法表现泰山之高，同一时间山南山北判若早晨和晚上。"
      },
      {
        "question": "王维《送綦毋潜落第还乡》中'东山客'和'采薇'分别指什么？",
        "answer": "'东山客'指隐居者（典出谢安隐居会稽东山），'采薇'指隐居生活（典出伯夷叔齐采薇而食）。"
      },
      {
        "question": "王维《渭川田家》最后一句'怅然吟式微'有何深意？",
        "answer": "借用《诗经》'式微'篇表达归隐之意，抒发对田园闲逸生活的向往。"
      },
      {
        "question": "“持谢邻家子，效颦安可希”中的“安可希”是什么意思？",
        "answer": "怎能希望别人的赏识。"
      },
      {
        "question": "《秋登兰山寄张五》中“天边树若荠”的“荠”指什么？",
        "answer": "野菜名，这里形容远望中天边树林的细小。"
      },
      {
        "question": "《夏日南亭怀辛大》中“恨无知音赏”表达了诗人怎样的情感？",
        "answer": "遗憾没有知音欣赏自己的琴声。"
      },
      {
        "question": "《宿业师山房待丁大不至》中“孤琴候萝径”描绘了怎样的场景？",
        "answer": "诗人独自抱着琴在藤萝掩映的小路上等候友人。"
      },
      {
        "question": "《同从弟南斋玩月忆山阴崔少府》中“苒苒几盈虚”的“盈虚”指什么？",
        "answer": "月亮的圆缺变化。"
      },
      {
        "question": "《寻西山隐者不遇》中“差池不相见”的“差池”是什么意思？",
        "answer": "此来彼往而错过。"
      },
      {
        "question": "《春泛若耶溪》中“生事且弥漫”表达了诗人怎样的态度？",
        "answer": "对世事渺茫的感慨，愿做渔翁隐居。"
      },
      {
        "question": "《宿王昌龄隐居》中“茅亭宿花影”的“宿”如何理解？",
        "answer": "比喻夜静花影如眠。"
      },
      {
        "question": "《与高适薛据登慈恩寺浮图》中“誓将挂冠去”的“挂冠”指什么？",
        "answer": "辞官归隐。"
      },
      {
        "question": "《贼退示官吏并序》中“井税有常期”反映了怎样的社会背景？",
        "answer": "太平时期田税征收有固定期限的安定生活。"
      },
      {
        "question": "《郡斋雨中与诸文士燕集》中“理会是非遣”体现了什么思想？",
        "answer": "通达事理后就能排遣是非纷扰。"
      },
      {
        "question": "《初发扬子寄元大校书》中“沿洄安得住”比喻什么？",
        "answer": "人生处境如同水中行舟，顺逆难料。"
      },
      {
        "question": "《寄全椒山中道士》中“煮白石”用了什么典故？",
        "answer": "《神仙传》中白石先生煮白石为粮的典故，指道士的清修生活。"
      },
      {
        "question": "《长安遇冯著》中“采山因买斧”暗指什么？",
        "answer": "隐居山林的生活。"
      },
      {
        "question": "《晨诣超师院读禅经》中“贝叶书”指什么？",
        "answer": "佛经。因古印度僧人常用贝多罗树叶写经，故称。"
      },
      {
        "question": "《塞下曲》的作者是谁？",
        "answer": "王昌龄"
      },
      {
        "question": "《塞下曲》中“饮马渡秋水，水寒风似刀”描绘了怎样的景象？",
        "answer": "描绘了边塞秋日饮马渡河的艰苦环境，水寒刺骨，风如刀割。"
      },
      {
        "question": "《关山月》中“汉下白登道，胡窥青海湾”涉及哪些历史事件？",
        "answer": "涉及刘邦被匈奴围困于白登山的历史事件，以及胡人窥视青海湾的边塞战事。"
      },
      {
        "question": "《子夜四时歌·秋歌》中“何日平胡虏，良人罢远征”表达了怎样的情感？",
        "answer": "表达了妻子对丈夫早日平定边患、结束远征归来的深切期盼。"
      },
      {
        "question": "《长干行》中“郎骑竹马来，绕床弄青梅”后来演化为什么成语？",
        "answer": "演化成成语“青梅竹马”，形容男女从小一起长大的亲密情谊。"
      },
      {
        "question": "《游子吟》中“谁言寸草心，报得三春晖”运用了什么修辞手法？",
        "answer": "运用了比喻手法，以小草比喻游子，春晖比喻母爱，表达母爱的深厚难以回报。"
      },
      {
        "question": "《登幽州台歌》中“念天地之悠悠，独怆然而涕下”体现了诗人怎样的心境？",
        "answer": "体现了诗人面对广漠宇宙时，深感人生短暂、孤独无依的悲怆心境。"
      },
      {
        "question": "《梦游天姥吟留别》中“安能摧眉折腰事权贵”表现了李白怎样的性格？",
        "answer": "表现了李白蔑视权贵、不愿卑躬屈膝的傲岸性格和追求自由的精神。"
      },
      {
        "question": "《听安万善吹觱篥歌》中提到的觱篥起源于哪里？",
        "answer": "觱篥起源于古代西域的龟兹国（今新疆库车一带）。"
      },
      {
        "question": "《庐山谣寄卢侍御虚舟》中“我本楚狂人，凤歌笑孔丘”用了什么典故？",
        "answer": "化用《论语》中楚国狂人接舆唱着“凤兮”之歌嘲讽孔子的典故，表明诗人的隐逸之志。"
      },
      {
        "question": "《金陵酒肆留别》的作者是谁？",
        "answer": "李白"
      },
      {
        "question": "《宣州谢脁楼饯别校书叔云》中'抽刀断水水更流'的下一句是什么？",
        "answer": "举杯销愁愁更愁"
      },
      {
        "question": "《白雪歌送武判官归京》中'忽如一夜春风来'的下一句是什么？",
        "answer": "千树万树梨花开"
      },
      {
        "question": "《丹青引赠曹将军霸》中'丹青不知老将至'的下一句是什么？",
        "answer": "富贵于我如浮云"
      },
      {
        "question": "《寄韩谏议》中'美人娟娟隔秋水'的下一句是什么？",
        "answer": "濯足洞庭望八荒"
      },
      {
        "question": "《古柏行》中'柯如青铜根如石'的上一句是什么？",
        "answer": "孔明庙前有老柏"
      },
      {
        "question": "《观公孙大娘弟子舞剑器行》中'一舞剑器动四方'的上一句是什么？",
        "answer": "昔有佳人公孙氏"
      },
      {
        "question": "《石鱼湖上醉歌》的作者是谁？",
        "answer": "元结"
      },
      {
        "question": "《石鱼湖》诗中提到的'长①风'中的'长'字注释是什么意思？",
        "answer": "助兴之意。"
      },
      {
        "question": "韩愈《山石》中'山石荦确行径微'的'荦确'是什么意思？",
        "answer": "险峻不平的样子。"
      },
      {
        "question": "《八月十五夜赠张功曹》中'嗣皇继圣登夔皋②'的'夔皋'指代什么？",
        "answer": "大舜的贤臣夔和皋陶。"
      },
      {
        "question": "《谒衡岳庙遂宿岳寺题门楼》中'五岳祭秩皆三公①'的'三公'指什么？",
        "answer": "指祭祀五岳要参照祭三公的等级来致祭。"
      },
      {
        "question": "《石鼓歌》中'搜于岐阳骋雄俊，万里禽兽皆遮罗①'的'遮罗'是什么意思？",
        "answer": "拦截捕捉。"
      },
      {
        "question": "柳宗元《渔翁》中'欸乃一声山水绿'的'欸乃'指什么？",
        "answer": "摇橹声或渔歌声。"
      },
      {
        "question": "《长恨歌》中'姊妹弟兄皆列土①'的'列土'是什么意思？",
        "answer": "分封土地。"
      },
      {
        "question": "《琵琶行》序言中提到的'湓浦口①'位于哪里？",
        "answer": "九江郡（今江西九江）。"
      },
      {
        "question": "《琵琶行》中'间关莺语花底滑②'的'间关'形容什么声音？",
        "answer": "形容鸟鸣声宛转。"
      },
      {
        "question": "《琵琶行》中'钿头银篦击节碎'的'钿头银篦'是什么？",
        "answer": "镶嵌金花的银质发梳。"
      },
      {
        "question": "《琵琶行》中哪句诗表达了诗人与琵琶女同病相怜的情感？",
        "answer": "同是天涯沦落人，相逢何必曾相识。"
      },
      {
        "question": "《韩碑》中提到的\"元和天子\"指的是哪位皇帝？",
        "answer": "唐宪宗。"
      },
      {
        "question": "《燕歌行》中\"汉家烟尘在东北\"一句中的\"汉家\"实际上指的是哪个朝代？",
        "answer": "唐朝。"
      },
      {
        "question": "《古从军行》中\"公主琵琶幽怨多\"一句提到的\"公主\"最可能是指哪位历史人物？",
        "answer": "细君公主或解忧公主等汉代和亲公主。"
      },
      {
        "question": "《洛阳女儿行》中\"意气骄奢剧季伦\"的\"季伦\"指的是哪位历史人物？",
        "answer": "西晋富豪石崇，字季伦。"
      },
      {
        "question": "《老将行》中\"肯数邺下黄须儿\"的\"黄须儿\"指的是谁？",
        "answer": "曹操的次子曹彰。"
      },
      {
        "question": "《蜀道难》中\"蚕丛及鱼凫\"指的是什么人物？",
        "answer": "传说中古蜀国的两位国王。"
      },
      {
        "question": "《长相思二首之二》中\"赵瑟初停凤凰柱\"的\"凤凰柱\"是什么？",
        "answer": "刻成凤凰形状的瑟柱。"
      },
      {
        "question": "《行路难》中\"闲来垂钓碧溪上\"暗用了哪位历史人物的典故？",
        "answer": "姜太公（吕尚）在渭水垂钓遇周文王的典故。"
      },
      {
        "question": "《桃源行》中\"渔舟逐水爱山春\"描写的是哪个著名典故？",
        "answer": "陶渊明《桃花源记》中武陵渔人发现桃花源的故事。"
      },
      {
        "question": "《行路难》中表达诗人对从政仍有所期待的诗句是什么？",
        "answer": "闲来垂钓碧溪上，忽复乘舟梦日边。"
      },
      {
        "question": "《将进酒》中表达人生得意应该尽情欢乐的诗句是什么？",
        "answer": "人生得意须尽欢，莫使金樽空对月。"
      },
      {
        "question": "《兵车行》中反映战争残酷的诗句是什么？",
        "answer": "边庭流血成海水，武皇开边意未已。"
      },
      {
        "question": "《丽人行》中描写贵族奢侈生活的诗句是什么？",
        "answer": "紫驼之峰出翠釜，水精之盘行素鳞。"
      },
      {
        "question": "《哀江头》中表达诗人对往昔繁华的怀念的诗句是什么？",
        "answer": "忆昔霓旌下南苑，苑中万物生颜色。"
      },
      {
        "question": "《哀王孙》中表达诗人对王孙命运的关切和忧虑的诗句是什么？",
        "answer": "哀哉王孙慎勿疏，五陵佳气无时无。"
      },
      {
        "question": "《望月怀远》中表达诗人对远方亲人思念的诗句是什么？",
        "answer": "海上生明月，天涯共此时。"
      },
      {
        "question": "《送杜少府之任蜀州》中表达友情不受距离限制的诗句是什么？",
        "answer": "海内存知己，天涯若比邻。"
      },
      {
        "question": "《在狱咏蝉》中表达诗人高洁品格的诗句是什么？",
        "answer": "无人信高洁，谁为表予心。"
      },
      {
        "question": "《和晋陵陆丞早春游望》中表达诗人对春天变化的敏感的诗句是什么？",
        "answer": "独有宦游人，偏惊物候新。"
      },
      {
        "question": "《题大庾岭北驿》的作者是谁？",
        "answer": "宋之问"
      },
      {
        "question": "《次北固山下》中“潮平两岸阔”的下一句是什么？",
        "answer": "风正一帆悬"
      },
      {
        "question": "《题破山寺后禅院》中“山光悦鸟性”的下一句是什么？",
        "answer": "潭影空人心"
      },
      {
        "question": "《赠孟浩然》中“红颜弃轩冕”的下一句是什么？",
        "answer": "白首卧松云"
      },
      {
        "question": "《渡荆门送别》中“月下飞天镜”的下一句是什么？",
        "answer": "云生结海楼"
      },
      {
        "question": "《送友人》中“青山横北郭”的下一句是什么？",
        "answer": "白水绕东城"
      },
      {
        "question": "《听蜀僧浚弹琴》中“为我一挥手”的下一句是什么？",
        "answer": "如听万壑松"
      },
      {
        "question": "《春望》中“国破山河在”的下一句是什么？",
        "answer": "城春草木深"
      },
      {
        "question": "《月夜忆舍弟》中“露从今夜白”的下一句是什么？",
        "answer": "月是故乡明"
      },
      {
        "question": "《山居秋暝》中“明月松间照”的下一句是什么？",
        "answer": "清泉石上流"
      },
      {
        "question": "《终南山》中“太乙近天都”的下一句是什么？",
        "answer": "连山到海隅"
      },
      {
        "question": "《汉江临眺》中“江流天地外”的下一句是什么？",
        "answer": "山色有无中"
      },
      {
        "question": "《题大庾岭北驿》中“阳月”指的是什么？",
        "answer": "阴历十月"
      },
      {
        "question": "《次北固山下》中“残夜”指的是什么？",
        "answer": "夜色已残，指天将破晓"
      },
      {
        "question": "《寄左省杜拾遗》中的“杜拾遗”指的是谁？",
        "answer": "杜甫"
      },
      {
        "question": "《赠孟浩然》中“中圣”是什么意思？",
        "answer": "“中圣人”的简称，即醉酒"
      },
      {
        "question": "《渡荆门送别》中“大荒”指的是什么？",
        "answer": "广阔的原野"
      },
      {
        "question": "《送友人》中“孤蓬”比喻什么？",
        "answer": "随风飘转的蓬草，常比喻飘泊无定的孤客"
      },
      {
        "question": "《夜泊牛渚怀古》中“谢将军”指的是谁？",
        "answer": "东晋谢尚"
      },
      {
        "question": "《月夜》中“鄜州”是现在的哪里？",
        "answer": "今陕西省富县"
      },
      {
        "question": "《终南别业》的作者是谁？",
        "answer": "王维"
      },
      {
        "question": "《终南别业》中\"行到水穷处\"的下一句是什么？",
        "answer": "坐看云起时"
      },
      {
        "question": "《望洞庭湖赠张丞相》中\"波撼岳阳城\"的上一句是什么？",
        "answer": "气蒸云梦泽"
      },
      {
        "question": "《与诸子登岘山》中提到的\"羊公碑\"是为纪念谁而建？",
        "answer": "西晋名将羊祜"
      },
      {
        "question": "《清明日宴梅道士房》中\"青鸟使\"指的是什么？",
        "answer": "梅道士派来的信使"
      },
      {
        "question": "《岁暮归南山》中\"青阳逼岁除\"的\"青阳\"指什么？",
        "answer": "春天"
      },
      {
        "question": "《过故人庄》中\"把酒话桑麻\"的上一句是什么？",
        "answer": "开轩面场圃"
      },
      {
        "question": "《秦中感秋寄远上人》中\"三径\"指什么？",
        "answer": "归隐后所住的田园"
      },
      {
        "question": "《宿桐庐江寄广陵旧游》中\"沧江\"指哪条江？",
        "answer": "桐庐江"
      },
      {
        "question": "《留别王侍御维》中\"当路谁相假\"的\"假\"是什么意思？",
        "answer": "帮助"
      },
      {
        "question": "《早寒江上有怀》中\"襄水曲\"指什么地方？",
        "answer": "汉水的转弯处"
      },
      {
        "question": "《秋日登吴公台上寺远眺》中\"南朝\"指哪几个朝代？",
        "answer": "宋、齐、梁、陈"
      },
      {
        "question": "《送李中丞归汉阳别业》中\"三边\"指唐代哪三个边境州？",
        "answer": "幽州、并州、凉州"
      },
      {
        "question": "《新年作》中\"长沙傅\"指谁？",
        "answer": "西汉贾谊"
      },
      {
        "question": "《送僧归日本》中\"法舟\"指什么？",
        "answer": "特指佛船"
      },
      {
        "question": "《谷口书斋寄杨补阙》中\"薜帷\"指什么？",
        "answer": "成片如帷帐的薜荔"
      },
      {
        "question": "《赋得暮雨送李胄》中\"散丝\"比喻什么？",
        "answer": "细雨，这里喻指流泪"
      },
      {
        "question": "《江乡故人偶集客舍》中\"羁旅\"指什么？",
        "answer": "犹漂泊"
      },
      {
        "question": "《送李端》中\"风尘\"指什么？",
        "answer": "指时世纷乱"
      },
      {
        "question": "《喜见外弟又言别》中\"沧海事\"比喻什么？",
        "answer": "比喻世事变迁"
      },
      {
        "question": "《云阳馆与韩绅宿别》中\"共传\"指什么？",
        "answer": "传杯共饮"
      },
      {
        "question": "《喜外弟卢纶见宿》中\"蔡家亲\"指什么？",
        "answer": "指表亲"
      },
      {
        "question": "《蜀先主庙》中\"五铢钱\"与哪位历史人物相关？",
        "answer": "汉武帝"
      },
      {
        "question": "《没蕃故人》中\"月支\"借指什么？",
        "answer": "吐蕃"
      },
      {
        "question": "《赋得古原草送别》中\"离离\"形容什么？",
        "answer": "形容草茂盛"
      },
      {
        "question": "《旅宿》中\"侵晓\"指什么时候？",
        "answer": "破晓"
      },
      {
        "question": "《秋日赴阙题潼关驿楼》中\"帝乡\"指哪里？",
        "answer": "都城长安"
      },
      {
        "question": "《早秋》中\"金河\"指什么？",
        "answer": "银河"
      },
      {
        "question": "《蝉》中'五更疏欲断，一树碧无情'的注释是什么？",
        "answer": "意为蝉声至五更时稀疏，而绿树无动于衷。"
      },
      {
        "question": "《风雨》中'心断新丰酒'的典故出自哪里？",
        "answer": "出自《旧唐书·马周传》，讲述马周在新丰逆旅独酌，后得太宗赏识的故事。"
      },
      {
        "question": "《落花》中'芳心向春尽，所得是沾衣'的'芳心'指什么？",
        "answer": "既指花，又指惜花之心。"
      },
      {
        "question": "《凉思》中'北斗兼春远'的'兼'是什么意思？",
        "answer": "与的意思。"
      },
      {
        "question": "《北青萝》中'世界微尘里，吾宁爱与憎'的'宁'是什么意思？",
        "answer": "为什么的意思。"
      },
      {
        "question": "《送人东游》中'荒戍落黄叶'的'荒戍'指什么？",
        "answer": "废弃的营垒。"
      },
      {
        "question": "《灞上秋居》中'寄卧郊扉久，何年致此身'的'致此身'指什么？",
        "answer": "指入仕为官。"
      },
      {
        "question": "《楚江怀古》中'云中君不见'的'云中君'是谁？",
        "answer": "云中君是楚辞中的云神，此处借指楚地古迹。"
      },
      {
        "question": "《书边事》中'蕃情似此水，长愿向南流'的喻义是什么？",
        "answer": "以南流之水比喻蕃情，希望吐蕃能长久地归附中央政权。"
      },
      {
        "question": "《巴山道中除夜有怀》中'明日岁华新'指什么？",
        "answer": "意为明天就是新年了。岁华指年华。"
      },
      {
        "question": "《孤雁》中'未必逢矰缴，孤飞自可疑'的'矰缴'指什么？",
        "answer": "泛指短箭。"
      },
      {
        "question": "《春宫怨》中'年年越溪女，相忆采芙蓉'的'越溪女'指谁？",
        "answer": "指西施。"
      },
      {
        "question": "《章台夜思》中'楚角'是什么？",
        "answer": "楚地曲调的角声。"
      },
      {
        "question": "《寻陆鸿渐不遇》中'归来每日斜'的'报道'是什么意思？",
        "answer": "回答道的意思。"
      },
      {
        "question": "《黄鹤楼》中'晴川历历汉阳树'的'历历'是什么意思？",
        "answer": "清晰、分明的样子。"
      },
      {
        "question": "《行经华阴》中'岧峣太华俯咸京'的'咸京'指哪里？",
        "answer": "指咸阳。"
      },
      {
        "question": "《望蓟门》中'少小虽非投笔吏'的典故人物是谁？",
        "answer": "指汉人班超。"
      },
      {
        "question": "《送魏万之京》中'御苑砧声向晚多'的'砧声'指什么声音？",
        "answer": "捣衣声。"
      },
      {
        "question": "《九日登望仙台呈刘明府》中'河上仙翁'指谁？",
        "answer": "指河上公。"
      },
      {
        "question": "《登金陵凤凰台》中'晋代衣冠成古丘'的'衣冠'指什么？",
        "answer": "指豪门贵族。"
      },
      {
        "question": "《送李少府贬峡中王少府贬长沙》中'圣代即今多雨露'的'雨露'喻指什么？",
        "answer": "比喻恩惠、恩泽。"
      },
      {
        "question": "《奉和中书舍人贾至早朝大明宫》中'凤凰池'指哪个机构？",
        "answer": "指中书省。"
      },
      {
        "question": "《和贾至舍人早朝大明宫之作》中'绛帻鸡人'是做什么的？",
        "answer": "古代宫中于天将亮时，头戴红巾的卫士在朱雀门外高声喊叫，以警百官，故名鸡人。"
      },
      {
        "question": "《奉和圣制从蓬莱向兴庆阁道中留春雨中春望之作应制》的作者是谁？",
        "answer": "王维"
      },
      {
        "question": "《积雨辋川庄作》中“漠漠水田飞白鹭”的下一句是什么？",
        "answer": "阴阴夏木啭黄鹂"
      },
      {
        "question": "《酬郭给事》中“洞门高阁霭余辉”的下一句是什么？",
        "answer": "桃李阴阴柳絮飞"
      },
      {
        "question": "《蜀相》中“丞相祠堂何处寻”的下一句是什么？",
        "answer": "锦官城外柏森森"
      },
      {
        "question": "《客至》中“花径不曾缘客扫”的下一句是什么？",
        "answer": "蓬门今始为君开"
      },
      {
        "question": "《野望》中“西山白雪三城戍”的下一句是什么？",
        "answer": "南浦清江万里桥"
      },
      {
        "question": "《闻官军收河南河北》中“剑外忽传收蓟北”的下一句是什么？",
        "answer": "初闻涕泪满衣裳"
      },
      {
        "question": "《登高》中“风急天高猿啸哀”的下一句是什么？",
        "answer": "渚清沙白鸟飞回"
      },
      {
        "question": "《登楼》中“花近高楼伤客心”的下一句是什么？",
        "answer": "万方多难此登临"
      },
      {
        "question": "《宿府》中“清秋幕府井梧寒”的下一句是什么？",
        "answer": "独宿江城蜡炬残"
      },
      {
        "question": "《阁夜》中“岁暮阴阳催短景”的下一句是什么？",
        "answer": "天涯霜雪霁寒霄"
      },
      {
        "question": "《咏怀古迹五首之一》中“支离东北风尘际”的下一句是什么？",
        "answer": "漂泊西南天地间"
      },
      {
        "question": "《咏怀古迹五首之二》中“摇落深知宋玉悲”的下一句是什么？",
        "answer": "风流儒雅亦吾师"
      },
      {
        "question": "《咏怀古迹五首之三》中“群山万壑赴荆门”的下一句是什么？",
        "answer": "生长明妃尚有村"
      },
      {
        "question": "《咏怀古迹五首之四》中“蜀主征吴幸三峡”的下一句是什么？",
        "answer": "崩年亦在永安宫"
      },
      {
        "question": "《咏怀古迹五首之五》中“诸葛大名垂宇宙”的下一句是什么？",
        "answer": "宗臣遗像肃清高"
      },
      {
        "question": "《江州重别薛六柳八二员外》中“生涯岂料承优诏”的下一句是什么？",
        "answer": "世事空知学醉歌"
      },
      {
        "question": "《长沙过贾谊宅》中“三年谪宦此栖迟”的下一句是什么？",
        "answer": "万古惟留楚客悲"
      },
      {
        "question": "《自夏口至鹦洲夕望岳阳寄源中丞》中“汀洲无浪复无烟”的下一句是什么？",
        "answer": "楚客相思益渺然"
      },
      {
        "question": "《赠阙下裴舍人》中“二月黄鹂飞上林”的下一句是什么？",
        "answer": "春城紫禁晓阴阴"
      },
      {
        "question": "《寄李儋元锡》中“去年花里逢君别”的下一句是什么？",
        "answer": "今日花开又一年"
      },
      {
        "question": "《同题仙游观》中“仙台初见五城楼”的下一句是什么？",
        "answer": "风物凄凄宿雨收"
      },
      {
        "question": "《春思》中“莺啼燕语报新年”的下一句是什么？",
        "answer": "马邑龙堆路几千"
      },
      {
        "question": "《晚次鄂州》中“云开远见汉阳城”的下一句是什么？",
        "answer": "犹是孤帆一日程"
      },
      {
        "question": "《登柳州城楼寄漳汀封连四州刺史》的作者是谁？",
        "answer": "柳宗元"
      },
      {
        "question": "《西塞山怀古》中提到的'千寻铁锁沉江底'中的'寻'指什么？",
        "answer": "古时八尺为一寻"
      },
      {
        "question": "《遣悲怀三首之一》中'自嫁黔娄百事乖'的'黔娄'指什么？",
        "answer": "战国时齐国的贫士，此处是元稹自喻"
      },
      {
        "question": "《锦瑟》中'沧海月明珠有泪'用了什么典故？",
        "answer": "典出《博物志》，据说南海有鲛人，水居如鱼，哭时眼泪成珠"
      },
      {
        "question": "《无题》诗中'心有灵犀一点通'的'灵犀'指什么？",
        "answer": "犀牛角中心有一条白纹贯通两端，古人视为灵异之物"
      },
      {
        "question": "《隋宫》中'地下若逢陈后主'的'陈后主'是谁？",
        "answer": "南朝陈最后一位皇帝陈叔宝"
      },
      {
        "question": "《筹笔驿》中'风云常为护储胥'的'储胥'指什么？",
        "answer": "指军用的篱栅"
      },
      {
        "question": "《春雨》中'玉珰缄札何由达'的'玉珰'是什么？",
        "answer": "耳珠，旧时常作为男女定情物"
      },
      {
        "question": "《苏武庙》中'回日楼台非甲帐'的'甲帐'指什么？",
        "answer": "汉武帝用珍宝装饰的帐幕，'非甲帐'意指汉武帝已死"
      },
      {
        "question": "《贫女》中'苦恨年年压金线'的'压金线'指什么？",
        "answer": "指刺绣"
      },
      {
        "question": "王维《鹿柴》诗中“返影”指的是什么？",
        "answer": "夕阳返照的光。"
      },
      {
        "question": "《竹里馆》中诗人独坐何处？",
        "answer": "幽深的竹林里。"
      },
      {
        "question": "王维《相思》诗中“撷”是什么意思？",
        "answer": "摘下，取下。"
      },
      {
        "question": "《杂诗》中“著花”指什么？",
        "answer": "开花。"
      },
      {
        "question": "李白《静夜思》中“疑是地上霜”的上一句是什么？",
        "answer": "床前明月光。"
      },
      {
        "question": "杜甫《八阵图》中“功盖三分国”下一句是什么？",
        "answer": "名成八阵图。"
      },
      {
        "question": "王之涣《登鹳雀楼》中“欲穷千里目”的下一句是？",
        "answer": "更上一层楼。"
      },
      {
        "question": "《枫桥夜泊》中“夜半钟声到客船”的上一句是什么？",
        "answer": "姑苏城外寒山寺。"
      },
      {
        "question": "李商隐《夜雨寄北》中“巴山夜雨涨秋池”的上一句是？",
        "answer": "君问归期未有期。"
      },
      {
        "question": "杜秋娘《金缕衣》中劝君惜取什么？",
        "answer": "少年时。"
      },
      {
        "question": "“红豆生南国”出自哪位诗人的作品？",
        "answer": "王维。"
      },
      {
        "question": "“千山鸟飞绝，万径人踪灭”出自哪首诗？",
        "answer": "柳宗元《江雪》。"
      },
      {
        "question": "“劝君更尽一杯酒，西出阳关无故人”是谁的诗句？",
        "answer": "王维。"
      },
      {
        "question": "“二十四桥明月夜”出自哪首诗？",
        "answer": "杜牧《寄扬州韩绰判官》。"
      },
      {
        "question": "“嫦娥应悔偷灵药”出自哪位诗人的作品？",
        "answer": "李商隐。"
      },
      {
        "question": "《凉州词》中“葡萄美酒夜光杯”的作者是谁？",
        "answer": "王翰。"
      },
      {
        "question": "“旧时王谢堂前燕”出自哪首诗？",
        "answer": "刘禹锡《乌衣巷》。"
      },
      {
        "question": "“春潮带雨晚来急”的下一句是什么？",
        "answer": "野渡无人舟自横。"
      },
      {
        "question": "“羌笛何须怨杨柳”出自哪位诗人的作品？",
        "answer": "王之涣。"
      },
      {
        "question": "“玉阶生白露”出自李白的哪首诗？",
        "answer": "《玉阶怨》。"
      }
    ],
    "processed_time": "2025-06-19 09:12:44"
  }
]